onegov.activity-1.19.2-py3.6-nspkg.pth
onegov/activity/.gitignore
onegov/activity/__init__.py
onegov/activity/errors.py
onegov/activity/iso20022.py
onegov/activity/upgrade.py
onegov/activity/utils.py
onegov/activity/collections/__init__.py
onegov/activity/collections/activity.py
onegov/activity/collections/attendee.py
onegov/activity/collections/booking.py
onegov/activity/collections/invoice.py
onegov/activity/collections/occasion.py
onegov/activity/collections/period.py
onegov/activity/collections/publication_request.py
onegov/activity/matching/__init__.py
onegov/activity/matching/core.py
onegov/activity/matching/interfaces.py
onegov/activity/matching/score.py
onegov/activity/matching/utils.py
onegov/activity/models/__init__.py
onegov/activity/models/activity.py
onegov/activity/models/age_barrier.py
onegov/activity/models/attendee.py
onegov/activity/models/booking.py
onegov/activity/models/invoice.py
onegov/activity/models/invoice_item.py
onegov/activity/models/invoice_reference.py
onegov/activity/models/occasion.py
onegov/activity/models/occasion_date.py
onegov/activity/models/occasion_need.py
onegov/activity/models/period.py
onegov/activity/models/publication_request.py
onegov/activity/tests/conftest.py
onegov/activity/tests/test_iso20022.py
onegov/activity/tests/test_matching_db.py
onegov/activity/tests/test_matching_memory.py
onegov/activity/tests/test_models.py
onegov/activity/tests/test_utils.py
onegov/activity/tests/fixtures/camt.053_P_CH0309000000250090342_380000000_0_2016053100163801.xml
onegov/activity/tests/fixtures/scenario.py
onegov.activity-1.19.2.dist-info/METADATA
onegov.activity-1.19.2.dist-info/WHEEL
onegov.activity-1.19.2.dist-info/entry_points.txt
onegov.activity-1.19.2.dist-info/namespace_packages.txt
onegov.activity-1.19.2.dist-info/top_level.txt
onegov.activity-1.19.2.dist-info/RECORD
